<?xml version = "1.0" encoding = "UTF-8" ?>
<mission id="prologue2" activeCheck ="true" shouldIgnoreSenderVerification="false">
<goals>
<goal type="delay" time="35.0"/>
</goals>

<nextMission IsSilent="false">Missions/Prologue/Prologue3.xml</nextMission>

<email>
<sender>G</sender>
<subject>案件档案</subject>
<body>欢迎使用你的"武器库"中最重要的工具——案件档案。这里是存储所有案件数据的地方，你遇到的任何重要数据都会自动上传到这里。当你开始一个案件时，你会看到案件简介、嫌疑人名单和他们的资料以及所有在初步调查中收集到的证据。很明显，你无法接触到这些证据，所以我们为你制作了精确的证据扫描件。

另外，看看你电脑上的程序。你会看到一堆不同的程序。这些程序大多是用来入侵计算机网络的。Nova并不是所有都...请求到许可。不过我想我们有合法的授权。

你还会看到一个叫MemForensics的程序。这个程序可以用来查看节点的内存转储，但我们也已经格式化了一些东西，比如证物。任何带有.md或图像文件扩展名的东西，比如.png或.jpg，你都可以用这个程序读取。运行这个程序的时候一定要看下图片那边。

总之，看一下一些案件文件，我一会再给你回复。
-G
</body>
<attachments>
</attachments>
</email>
</mission>